pytest_diff.py
pytest_diff-0.1.14.dist-info/LICENSE
pytest_diff-0.1.14.dist-info/METADATA
pytest_diff-0.1.14.dist-info/WHEEL
pytest_diff-0.1.14.dist-info/entry_points.txt
pytest_diff-0.1.14.dist-info/top_level.txt
pytest_diff-0.1.14.dist-info/RECORD
